hapi/__init__.py
hapi/chart/__init__.py
hapi/chart/chart_pb2.py
hapi/chart/chart_pb2_grpc.py
hapi/chart/config_pb2.py
hapi/chart/config_pb2_grpc.py
hapi/chart/metadata_pb2.py
hapi/chart/metadata_pb2_grpc.py
hapi/chart/template_pb2.py
hapi/chart/template_pb2_grpc.py
hapi/release/__init__.py
hapi/release/hook_pb2.py
hapi/release/hook_pb2_grpc.py
hapi/release/info_pb2.py
hapi/release/info_pb2_grpc.py
hapi/release/release_pb2.py
hapi/release/release_pb2_grpc.py
hapi/release/status_pb2.py
hapi/release/status_pb2_grpc.py
hapi/release/test_run_pb2.py
hapi/release/test_run_pb2_grpc.py
hapi/release/test_suite_pb2.py
hapi/release/test_suite_pb2_grpc.py
hapi/services/__init__.py
hapi/services/tiller_pb2.py
hapi/services/tiller_pb2_grpc.py
hapi/version/__init__.py
hapi/version/version_pb2.py
hapi/version/version_pb2_grpc.py
pyhelm/__init__.py
pyhelm/chartbuilder.py
pyhelm/logger.py
pyhelm/repo.py
pyhelm/tiller.py
pyhelm/tls.py
pyhelm-0.1.0.dist-info/AUTHORS
pyhelm-0.1.0.dist-info/LICENSE
pyhelm-0.1.0.dist-info/METADATA
pyhelm-0.1.0.dist-info/WHEEL
pyhelm-0.1.0.dist-info/pbr.json
pyhelm-0.1.0.dist-info/top_level.txt
pyhelm-0.1.0.dist-info/RECORD
