Metadata-Version: 2.1
Name: pyhelm
Version: 0.1.0
Summary: Python bindings for Helm: Kubernetes package manager
Home-page: https://github.com/flaper87/pyhelm
Author: OpenStack
Author-email: openstack-dev@lists.openstack.org
Maintainer: Yaniv Oliver
Maintainer-email: yanivoliver@gmail.com
License: UNKNOWN
Platform: UNKNOWN
Classifier: Intended Audience :: Information Technology
Classifier: Intended Audience :: System Administrators
Classifier: License :: OSI Approved :: Apache Software License
Classifier: Operating System :: POSIX :: Linux
Classifier: Programming Language :: Python
Classifier: Programming Language :: Python :: 2
Classifier: Programming Language :: Python :: 2.7
Classifier: Programming Language :: Python :: 3
Classifier: Programming Language :: Python :: 3.5
Classifier: Programming Language :: Python :: 3.6
Classifier: Programming Language :: Python :: 3.7
Requires-Dist: gitpython
Requires-Dist: grpcio
Requires-Dist: grpcio-tools
Requires-Dist: protobuf
Requires-Dist: supermutes
Requires-Dist: requests
Requires-Dist: PyYAML
Requires-Dist: boto3
Requires-Dist: botocore
